BridgeAccesslib/__init__.py
BridgeAccesslib/comm.py
BridgeAccesslib/extended_comm.py
BridgeAccesslib/data_convert/__init__.py
BridgeAccesslib/data_convert/chip_bitmap_pos.py
BridgeAccesslib/data_convert/data_swap.py
DDBridgeAccesslib-0.1.0.dist-info/METADATA
DDBridgeAccesslib-0.1.0.dist-info/WHEEL
DDBridgeAccesslib-0.1.0.dist-info/top_level.txt
DDBridgeAccesslib-0.1.0.dist-info/RECORD
